pydrolono/__init__.py
pydrolono/client.py
pydrolono/exceptions.py
pydrolono-0.1.0.dist-info/LICENSE
pydrolono-0.1.0.dist-info/METADATA
pydrolono-0.1.0.dist-info/WHEEL
pydrolono-0.1.0.dist-info/top_level.txt
pydrolono-0.1.0.dist-info/RECORD
