Metadata-Version: 2.1
Name: pydrolono
Version: 0.1.0
Summary: A Python client for accessing hydrological data from NVE's Hydrology API
Home-page: https://github.com/paulskeie/pydrolono
Author: Paul Skeie
Author-email: paul.skeie@gmail.com
Project-URL: Bug Tracker, https://github.com/paulskeie/pydrolono/issues
Project-URL: Documentation, https://github.com/paulskeie/pydrolono#readme
Project-URL: Source Code, https://github.com/paulskeie/pydrolono
Classifier: Development Status :: 3 - Alpha
Classifier: Intended Audience :: Science/Research
Classifier: License :: OSI Approved :: MIT License
Classifier: Operating System :: OS Independent
Classifier: Programming Language :: Python :: 3
Classifier: Programming Language :: Python :: 3.8
Classifier: Programming Language :: Python :: 3.9
Classifier: Programming Language :: Python :: 3.10
Classifier: Topic :: Scientific/Engineering :: Hydrology
Requires-Python: >=3.8
License-File: LICENSE
Requires-Dist: pandas>=2.0.0
Requires-Dist: requests>=2.31.0
Requires-Dist: pytest>=7.0.0
Requires-Dist: pytest-cov>=4.0.0
Requires-Dist: flask>=2.0.0
